embed_builder/__init__.py
embed_builder-1.4.0.dist-info/LICENSE
embed_builder-1.4.0.dist-info/METADATA
embed_builder-1.4.0.dist-info/WHEEL
embed_builder-1.4.0.dist-info/top_level.txt
embed_builder-1.4.0.dist-info/RECORD
