Metadata-Version: 2.1
Name: embed-builder
Version: 1.4.0
Summary: Easily build Discord Embed dictionaries
Author: depthbomb
Project-URL: Repository, https://github.com/depthbomb/embed_builder
Keywords: discord
Classifier: Development Status :: 5 - Production/Stable
Classifier: Intended Audience :: Developers
Classifier: License :: OSI Approved :: MIT License
Classifier: Natural Language :: English
Classifier: Programming Language :: Python :: 3
Classifier: Programming Language :: Python :: 3.10
Classifier: Topic :: Software Development
Classifier: Topic :: Software Development :: Libraries
Classifier: Topic :: Software Development :: Libraries :: Python Modules
Classifier: Topic :: Utilities
Requires-Python: >=3.10
License-File: LICENSE
